setup.py
grr_response_proto/__init__.py
grr_response_proto/acls_pb2.py
grr_response_proto/analysis_pb2.py
grr_response_proto/api_call_router_pb2.py
grr_response_proto/api_utils_pb2.py
grr_response_proto/artifact_pb2.py
grr_response_proto/auto_export_pb2.py
grr_response_proto/cloud_pb2.py
grr_response_proto/config_file_pb2.py
grr_response_proto/config_pb2.py
grr_response_proto/containers_pb2.py
grr_response_proto/crowdstrike_pb2.py
grr_response_proto/data_store_pb2.py
grr_response_proto/deprecated_pb2.py
grr_response_proto/distro_pb2.py
grr_response_proto/dummy_pb2.py
grr_response_proto/export_pb2.py
grr_response_proto/flows_pb2.py
grr_response_proto/hunts_pb2.py
grr_response_proto/jobs_pb2.py
grr_response_proto/knowledge_base_pb2.py
grr_response_proto/large_file_pb2.py
grr_response_proto/objects_pb2.py
grr_response_proto/osquery_pb2.py
grr_response_proto/output_plugin_pb2.py
grr_response_proto/pipes_pb2.py
grr_response_proto/read_low_level_pb2.py
grr_response_proto/rrg_pb2.py
grr_response_proto/semantic_pb2.py
grr_response_proto/signed_commands_pb2.py
grr_response_proto/sysinfo_pb2.py
grr_response_proto/tests_pb2.py
grr_response_proto/timeline_pb2.py
grr_response_proto/user_pb2.py
grr_response_proto.egg-info/PKG-INFO
grr_response_proto.egg-info/SOURCES.txt
grr_response_proto.egg-info/dependency_links.txt
grr_response_proto.egg-info/requires.txt
grr_response_proto.egg-info/top_level.txt
grr_response_proto/api/__init__.py
grr_response_proto/api/artifact_pb2.py
grr_response_proto/api/client_pb2.py
grr_response_proto/api/config_pb2.py
grr_response_proto/api/cron_pb2.py
grr_response_proto/api/flow_pb2.py
grr_response_proto/api/hunt_pb2.py
grr_response_proto/api/metadata_pb2.py
grr_response_proto/api/osquery_pb2.py
grr_response_proto/api/output_plugin_pb2.py
grr_response_proto/api/reflection_pb2.py
grr_response_proto/api/signed_commands_pb2.py
grr_response_proto/api/timeline_pb2.py
grr_response_proto/api/user_pb2.py
grr_response_proto/api/vfs_pb2.py
grr_response_proto/api/yara_pb2.py
grr_response_proto/api/root/__init__.py
grr_response_proto/api/root/binary_management_pb2.py
grr_response_proto/api/root/user_management_pb2.py
grr_response_proto/rrg/__init__.py
