Metadata-Version: 2.4
Name: grr-response-proto
Version: 4.0.0.post0
Summary: GRR API client library
Home-page: https://github.com/google/grr/tree/master/proto
Maintainer: GRR Development Team
Maintainer-email: grr-dev@googlegroups.com
License: Apache License, Version 2.0
Requires-Dist: protobuf<4,>=3.20.3
Dynamic: home-page
Dynamic: license
Dynamic: maintainer
Dynamic: maintainer-email
Dynamic: requires-dist
Dynamic: summary
